saudiaddress/__init__.py
saudiaddress/__version__.py
saudiaddress/api.py
saudiaddress/models.py
saudiaddress-0.1.4.dist-info/DESCRIPTION.rst
saudiaddress-0.1.4.dist-info/METADATA
saudiaddress-0.1.4.dist-info/RECORD
saudiaddress-0.1.4.dist-info/WHEEL
saudiaddress-0.1.4.dist-info/metadata.json
saudiaddress-0.1.4.dist-info/top_level.txt
