Metadata-Version: 2.0
Name: saudiaddress
Version: 0.1.4
Summary: A simple Python wrapper for the Saudi National Address APIs.
Home-page: https://github.com/abduhbm/saudiaddress
Author: Abdulelah Bin Mahfoodh
Author-email: UNKNOWN
License: MIT
Keywords: Saudi National Address
Platform: UNKNOWN
Classifier: Development Status :: 3 - Alpha
Classifier: License :: OSI Approved :: MIT License
Classifier: Programming Language :: Python
Classifier: Programming Language :: Python :: 2.7
Classifier: Programming Language :: Python :: 3
Classifier: Programming Language :: Python :: 3.6
Classifier: Topic :: Utilities
Requires-Dist: requests
